README.rst
setup.cfg
setup.py
Flask_JWT.egg-info/PKG-INFO
Flask_JWT.egg-info/SOURCES.txt
Flask_JWT.egg-info/dependency_links.txt
Flask_JWT.egg-info/not-zip-safe
Flask_JWT.egg-info/requires.txt
Flask_JWT.egg-info/top_level.txt
flask_jwt/__init__.py