Metadata-Version: 1.1
Name: Flask-JWT
Version: 0.1.0
Summary: JWT token authentication for Flask apps
Home-page: https://github.com/mattupstate/flask-jwt
Author: Matt Wright
Author-email: matt@nobien.net
License: MIT
Platform: any
Classifier: Development Status :: 4 - Beta
Classifier: Environment :: Web Environment
Classifier: Intended Audience :: Developers
Classifier: License :: OSI Approved :: MIT License
Classifier: Operating System :: OS Independent
Classifier: Programming Language :: Python
Classifier: Topic :: Internet :: WWW/HTTP :: Dynamic Content
Classifier: Topic :: Software Development :: Libraries :: Python Modules
